imgenx/factory.py
imgenx/main.py
imgenx/operator.py
imgenx/oss_service.py
imgenx/script.py
imgenx/server.py
imgenx/predictor/base/base_image_analyzer.py
imgenx/predictor/base/base_image_generator.py
imgenx/predictor/base/base_video_generator.py
imgenx/predictor/generators/doubao_image_analyzer.py
imgenx/predictor/generators/doubao_image_generator.py
imgenx/predictor/generators/doubao_video_generator.py
imgenx_mcp-0.4.2.dist-info/METADATA
imgenx_mcp-0.4.2.dist-info/WHEEL
imgenx_mcp-0.4.2.dist-info/entry_points.txt
imgenx_mcp-0.4.2.dist-info/licenses/LICENSE
imgenx_mcp-0.4.2.dist-info/RECORD
