Metadata-Version: 2.4
Name: imgenx-mcp
Version: 0.4.2
Summary: AI Image/Video Generation MCP Server with OSS Upload - Powered by Doubao API
Project-URL: Homepage, https://github.com/helios123/imgenx-mcp
Project-URL: Repository, https://github.com/helios123/imgenx-mcp
Project-URL: Issues, https://github.com/helios123/imgenx-mcp/issues
Project-URL: Documentation, https://github.com/helios123/imgenx-mcp/blob/main/README.md
Author-email: helios123 <your-email@example.com>
License: MIT
License-File: LICENSE
Keywords: ai,aliyun,doubao,image-generation,mcp,oss,video-generation
Classifier: Development Status :: 4 - Beta
Classifier: Intended Audience :: Developers
Classifier: License :: OSI Approved :: MIT License
Classifier: Programming Language :: Python :: 3
Classifier: Programming Language :: Python :: 3.10
Classifier: Programming Language :: Python :: 3.11
Classifier: Programming Language :: Python :: 3.12
Requires-Python: >=3.10
Requires-Dist: fastmcp>=2.12.4
Requires-Dist: oss2>=2.19.1
Requires-Dist: pillow>=12.0.0
Requires-Dist: python-dotenv>=1.1.1
Requires-Dist: requests>=2.25.0
Requires-Dist: volcengine-python-sdk[ark]>=4.0.22
